Sae203_Arnaud/__init__.py
Sae203_Arnaud/aggreg.py
Sae203_Arnaud/cli.py
Sae203_Arnaud/filetools.py
Sae203_Arnaud/data/base.html
Sae203_Arnaud/data/config.yml
Sae203_Arnaud/data/feed.css
Sae203_Arnaud-1.0.11.dist-info/LICENCE
Sae203_Arnaud-1.0.11.dist-info/METADATA
Sae203_Arnaud-1.0.11.dist-info/WHEEL
Sae203_Arnaud-1.0.11.dist-info/entry_points.txt
Sae203_Arnaud-1.0.11.dist-info/top_level.txt
Sae203_Arnaud-1.0.11.dist-info/RECORD
