Metadata-Version: 2.1
Name: Sae203_Arnaud
Version: 1.0.11
Summary: Récupération d'un certain type de fux rss, affichage d'une synthèse sur une page web
Home-page: https://etulab.univ-amu.fr/g23015097/sae203_python
Author: Arnaud G
Author-email: arnaud.gaillard@etu.univ-amu.fr
Requires-Python: >=3.8
License-File: LICENCE
Requires-Dist: requests >=2.31.0
Requires-Dist: feedparser >=6.0.8
Requires-Dist: pyyaml >=6.0.1
Requires-Dist: beautifulsoup4 >=4.12.2
Requires-Dist: pytz >=2024.1
Requires-Dist: click >=8.1.7
Requires-Dist: inquirer >=3.2.4
